KN_TTS/__init__.py
KN_TTS/static/script.js
KN_TTS-0.1.0.dist-info/METADATA
KN_TTS-0.1.0.dist-info/WHEEL
KN_TTS-0.1.0.dist-info/entry_points.txt
KN_TTS-0.1.0.dist-info/top_level.txt
KN_TTS-0.1.0.dist-info/RECORD
